RTL/clk_divider/int_clk_div.v
module int_clk_div(
    input i_ref_clk,
    input i_rst_n,
    input i_clk_en,
    input [7:0] i_div_ratio,
    output o_div_clk
);
wire clk_div_en;
wire odd;
wire [7:0] half_togg;
wire [7:0] half_togg_pl;
reg [7:0] counter;
reg flag;
reg div_clk_reg;
assign o_div_clk = (!i_rst_n)? 1'b0 :(i_clk_en && (i_div_ratio > 1)) ? div_clk_reg : i_ref_clk;
assign clk_div_en = i_clk_en && ( i_div_ratio != 0) && ( i_div_ratio != 1);
assign odd = i_div_ratio[0];
assign half_togg = i_div_ratio >> 1;
assign half_togg_pl = i_div_ratio - half_togg;

always @(posedge i_ref_clk or negedge i_rst_n) begin
    if (!i_rst_n)begin
        div_clk_reg <= 1'h0;
        counter <= 8'h0 ;
        flag <= 1'h0 ;
    end
    else if(clk_div_en)begin
        if (!odd && counter == half_togg-1)begin
            div_clk_reg <=! o_div_clk ;
            counter <= 'h0 ;
        end
        else if (odd && ((counter == half_togg-1 && flag) || (counter == half_togg_pl-1 && !flag)))begin
            div_clk_reg <= ! o_div_clk ;
            counter <= 'h0 ;
            flag <= !flag ;
        end
        else
            counter <= counter + 'h1 ;
    end
    else begin
        counter   <= 8'd0;
        flag      <= 1'b0;
    end
end
endmodule

RTL/clk_divider/int_clk_div_tb.v
`timescale 1ns/1ps
module int_clk_div_tb();
    reg i_ref_clk;
    reg i_rst_n;
    reg i_clk_en;
    reg [7:0] i_div_ratio;
    wire o_div_clk;

int_clk_div DUT(
    .i_ref_clk (i_ref_clk),
    .i_rst_n   (i_rst_n),
    .i_clk_en  (i_clk_en),
    .i_div_ratio(i_div_ratio),
    .o_div_clk (o_div_clk)
);


always #5 i_ref_clk =~i_ref_clk;

initial begin
    $dumpfile("clk_div_DUMP.vcd") ;       
    $dumpvars; 
    initialize_ports();
    reset();
    randomize_inputs(0,2);

    randomize_inputs(1,2);
    randomize_inputs(1,4);
    randomize_inputs(1,6);
    
    randomize_inputs(0,4);
    randomize_inputs(1,3);
    randomize_inputs(1,5);
    randomize_inputs(1,7);
    randomize_inputs(1,1);

$stop;
end

task initialize_ports();
begin
    i_ref_clk =0;
    i_rst_n =0;
    i_clk_en =0;
    i_div_ratio =1;
    @(negedge i_ref_clk);
end
endtask

task reset();
begin
    i_rst_n =0;
    @(negedge i_ref_clk);
    i_rst_n =1;
    @(negedge i_ref_clk);
end
endtask

task randomize_inputs(input clk_en, input [7:0] div_ratio);
begin
    i_clk_en    = clk_en;
    i_div_ratio = div_ratio;
    repeat(20)@(negedge i_ref_clk);
end
endtask

endmodule

RTL/clk_divider/clk_div_DUMP.vcd
$date
	Thu Aug 28 15:55:58 2025
$end
$version
	QuestaSim Version 2021.1
$end
$timescale
	1ps
$end

$scope module int_clk_div_tb $end
$var reg 1 ! i_ref_clk $end
$var reg 1 " i_rst_n $end
$var reg 1 # i_clk_en $end
$var reg 8 $ i_div_ratio [7:0] $end
$var wire 1 % o_div_clk $end

$scope task initialize_ports $end
$upscope $end

$scope task reset $end
$upscope $end

$scope task randomize_inputs $end
$var reg 1 & clk_en $end
$var reg 8 ' div_ratio [7:0] $end
$upscope $end

$scope module DUT $end
$var wire 1 ( i_ref_clk $end
$var wire 1 ) i_rst_n $end
$var wire 1 * i_clk_en $end
$var wire 1 + i_div_ratio [7] $end
$var wire 1 , i_div_ratio [6] $end
$var wire 1 - i_div_ratio [5] $end
$var wire 1 . i_div_ratio [4] $end
$var wire 1 / i_div_ratio [3] $end
$var wire 1 0 i_div_ratio [2] $end
$var wire 1 1 i_div_ratio [1] $end
$var wire 1 2 i_div_ratio [0] $end
$var wire 1 % o_div_clk $end
$var wire 1 3 clk_div_en $end
$var wire 1 4 odd $end
$var wire 1 5 half_togg [7] $end
$var wire 1 6 half_togg [6] $end
$var wire 1 7 half_togg [5] $end
$var wire 1 8 half_togg [4] $end
$var wire 1 9 half_togg [3] $end
$var wire 1 : half_togg [2] $end
$var wire 1 ; half_togg [1] $end
$var wire 1 < half_togg [0] $end
$var wire 1 = half_togg_pl [7] $end
$var wire 1 > half_togg_pl [6] $end
$var wire 1 ? half_togg_pl [5] $end
$var wire 1 @ half_togg_pl [4] $end
$var wire 1 A half_togg_pl [3] $end
$var wire 1 B half_togg_pl [2] $end
$var wire 1 C half_togg_pl [1] $end
$var wire 1 D half_togg_pl [0] $end
$var reg 8 E counter [7:0] $end
$var reg 1 F flag $end
$var reg 1 G div_clk_reg $end
$upscope $end
$upscope $end
$enddefinitions $end
#0
$dumpvars
0!
0"
0#
b1 $
b0 E
0F
0G
x&
bx '
0%
03
14
0<
0;
0:
09
08
07
06
05
1D
0C
0B
0A
0@
0?
0>
0=
12
01
00
0/
0.
0-
0,
0+
0*
0)
0(
$end
#5000
1!
1(
#10000
0!
0(
#15000
1!
1(
#20000
0!
0(
1"
1)
#25000
1!
1(
1%
#30000
0!
0(
0%
0&
b10 '
b10 $
02
11
04
1<
0D
1C
1D
0C
#35000
1!
1(
1%
#40000
0!
0(
0%
#45000
1!
1(
1%
#50000
0!
0(
0%
#55000
1!
1(
1%
#60000
0!
0(
0%
#65000
1!
1(
1%
#70000
0!
0(
0%
#75000
1!
1(
1%
#80000
0!
0(
0%
#85000
1!
1(
1%
#90000
0!
0(
0%
#95000
1!
1(
1%
#100000
0!
0(
0%
#105000
1!
1(
1%
#110000
0!
0(
0%
#115000
1!
1(
1%
#120000
0!
0(
0%
#125000
1!
1(
1%
#130000
0!
0(
0%
#135000
1!
1(
1%
#140000
0!
0(
0%
#145000
1!
1(
1%
#150000
0!
0(
0%
#155000
1!
1(
1%
#160000
0!
0(
0%
#165000
1!
1(
1%
#170000
0!
0(
0%
#175000
1!
1(
1%
#180000
0!
0(
0%
#185000
1!
1(
1%
#190000
0!
0(
0%
#195000
1!
1(
1%
#200000
0!
0(
0%
#205000
1!
1(
1%
#210000
0!
0(
0%
#215000
1!
1(
1%
#220000
0!
0(
0%
#225000
1!
1(
1%
#230000
0!
0(
0%
1&
1#
1*
13
#235000
1!
1(
1G
1%
#240000
0!
0(
#245000
1!
1(
0G
0%
#250000
0!
0(
#255000
1!
1(
1G
1%
#260000
0!
0(
#265000
1!
1(
0G
0%
#270000
0!
0(
#275000
1!
1(
1G
1%
#280000
0!
0(
#285000
1!
1(
0G
0%
#290000
0!
0(
#295000
1!
1(
1G
1%
#300000
0!
0(
#305000
1!
1(
0G
0%
#310000
0!
0(
#315000
1!
1(
1G
1%
#320000
0!
0(
#325000
1!
1(
0G
0%
#330000
0!
0(
#335000
1!
1(
1G
1%
#340000
0!
0(
#345000
1!
1(
0G
0%
#350000
0!
0(
#355000
1!
1(
1G
1%
#360000
0!
0(
#365000
1!
1(
0G
0%
#370000
0!
0(
#375000
1!
1(
1G
1%
#380000
0!
0(
#385000
1!
1(
0G
0%
#390000
0!
0(
#395000
1!
1(
1G
1%
#400000
0!
0(
#405000
1!
1(
0G
0%
#410000
0!
0(
#415000
1!
1(
1G
1%
#420000
0!
0(
#425000
1!
1(
0G
0%
#430000
0!
0(
b100 '
b100 $
01
10
0<
1;
1C
0D
#435000
1!
1(
b1 E
#440000
0!
0(
#445000
1!
1(
1G
b0 E
1%
#450000
0!
0(
#455000
1!
1(
b1 E
#460000
0!
0(
#465000
1!
1(
0G
b0 E
0%
#470000
0!
0(
#475000
1!
1(
b1 E
#480000
0!
0(
#485000
1!
1(
1G
b0 E
1%
#490000
0!
0(
#495000
1!
1(
b1 E
#500000
0!
0(
#505000
1!
1(
0G
b0 E
0%
#510000
0!
0(
#515000
1!
1(
b1 E
#520000
0!
0(
#525000
1!
1(
1G
b0 E
1%
#530000
0!
0(
#535000
1!
1(
b1 E
#540000
0!
0(
#545000
1!
1(
0G
b0 E
0%
#550000
0!
0(
#555000
1!
1(
b1 E
#560000
0!
0(
#565000
1!
1(
1G
b0 E
1%
#570000
0!
0(
#575000
1!
1(
b1 E
#580000
0!
0(
#585000
1!
1(
0G
b0 E
0%
#590000
0!
0(
#595000
1!
1(
b1 E
#600000
0!
0(
#605000
1!
1(
1G
b0 E
1%
#610000
0!
0(
#615000
1!
1(
b1 E
#620000
0!
0(
#625000
1!
1(
0G
b0 E
0%
#630000
0!
0(
b110 '
b110 $
11
1<
0C
1B
1D
1C
0B
#635000
1!
1(
b1 E
#640000
0!
0(
#645000
1!
1(
b10 E
#650000
0!
0(
#655000
1!
1(
1G
b0 E
1%
#660000
0!
0(
#665000
1!
1(
b1 E
#670000
0!
0(
#675000
1!
1(
b10 E
#680000
0!
0(
#685000
1!
1(
0G
b0 E
0%
#690000
0!
0(
#695000
1!
1(
b1 E
#700000
0!
0(
#705000
1!
1(
b10 E
#710000
0!
0(
#715000
1!
1(
1G
b0 E
1%
#720000
0!
0(
#725000
1!
1(
b1 E
#730000
0!
0(
#735000
1!
1(
b10 E
#740000
0!
0(
#745000
1!
1(
0G
b0 E
0%
#750000
0!
0(
#755000
1!
1(
b1 E
#760000
0!
0(
#765000
1!
1(
b10 E
#770000
0!
0(
#775000
1!
1(
1G
b0 E
1%
#780000
0!
0(
#785000
1!
1(
b1 E
#790000
0!
0(
#795000
1!
1(
b10 E
#800000
0!
0(
#805000
1!
1(
0G
b0 E
0%
#810000
0!
0(
#815000
1!
1(
b1 E
#820000
0!
0(
#825000
1!
1(
b10 E
#830000
0!
0(
0&
b100 '
0#
b100 $
0*
01
03
0<
0C
0D
1C
#835000
1!
1(
1%
b0 E
#840000
0!
0(
0%
#845000
1!
1(
1%
#850000
0!
0(
0%
#855000
1!
1(
1%
#860000
0!
0(
0%
#865000
1!
1(
1%
#870000
0!
0(
0%
#875000
1!
1(
1%
#880000
0!
0(
0%
#885000
1!
1(
1%
#890000
0!
0(
0%
#895000
1!
1(
1%
#900000
0!
0(
0%
#905000
1!
1(
1%
#910000
0!
0(
0%
#915000
1!
1(
1%
#920000
0!
0(
0%
#925000
1!
1(
1%
#930000
0!
0(
0%
#935000
1!
1(
1%
#940000
0!
0(
0%
#945000
1!
1(
1%
#950000
0!
0(
0%
#955000
1!
1(
1%
#960000
0!
0(
0%
#965000
1!
1(
1%
#970000
0!
0(
0%
#975000
1!
1(
1%
#980000
0!
0(
0%
#985000
1!
1(
1%
#990000
0!
0(
0%
#995000
1!
1(
1%
#1000000
0!
0(
0%
#1005000
1!
1(
1%
#1010000
0!
0(
0%
#1015000
1!
1(
1%
#1020000
0!
0(
0%
#1025000
1!
1(
1%
#1030000
0!
0(
0%
1&
b11 '
1#
b11 $
1*
12
11
00
14
13
1<
0;
1D
0C
0D
1C
#1035000
1!
1(
b1 E
#1040000
0!
0(
#1045000
1!
1(
1G
b0 E
1F
1%
#1050000
0!
0(
#1055000
1!
1(
0G
0F
0%
#1060000
0!
0(
#1065000
1!
1(
b1 E
#1070000
0!
0(
#1075000
1!
1(
1G
b0 E
1F
1%
#1080000
0!
0(
#1085000
1!
1(
0G
0F
0%
#1090000
0!
0(
#1095000
1!
1(
b1 E
#1100000
0!
0(
#1105000
1!
1(
1G
b0 E
1F
1%
#1110000
0!
0(
#1115000
1!
1(
0G
0F
0%
#1120000
0!
0(
#1125000
1!
1(
b1 E
#1130000
0!
0(
#1135000
1!
1(
1G
b0 E
1F
1%
#1140000
0!
0(
#1145000
1!
1(
0G
0F
0%
#1150000
0!
0(
#1155000
1!
1(
b1 E
#1160000
0!
0(
#1165000
1!
1(
1G
b0 E
1F
1%
#1170000
0!
0(
#1175000
1!
1(
0G
0F
0%
#1180000
0!
0(
#1185000
1!
1(
b1 E
#1190000
0!
0(
#1195000
1!
1(
1G
b0 E
1F
1%
#1200000
0!
0(
#1205000
1!
1(
0G
0F
0%
#1210000
0!
0(
#1215000
1!
1(
b1 E
#1220000
0!
0(
#1225000
1!
1(
1G
b0 E
1F
1%
#1230000
0!
0(
b101 '
b101 $
01
10
0<
1;
0C
1B
1D
1C
0B
#1235000
1!
1(
b1 E
#1240000
0!
0(
#1245000
1!
1(
0G
b0 E
0F
0%
#1250000
0!
0(
#1255000
1!
1(
b1 E
#1260000
0!
0(
#1265000
1!
1(
b10 E
#1270000
0!
0(
#1275000
1!
1(
1G
b0 E
1F
1%
#1280000
0!
0(
#1285000
1!
1(
b1 E
#1290000
0!
0(
#1295000
1!
1(
0G
b0 E
0F
0%
#1300000
0!
0(
#1305000
1!
1(
b1 E
#1310000
0!
0(
#1315000
1!
1(
b10 E
#1320000
0!
0(
#1325000
1!
1(
1G
b0 E
1F
1%
#1330000
0!
0(
#1335000
1!
1(
b1 E
#1340000
0!
0(
#1345000
1!
1(
0G
b0 E
0F
0%
#1350000
0!
0(
#1355000
1!
1(
b1 E
#1360000
0!
0(
#1365000
1!
1(
b10 E
#1370000
0!
0(
#1375000
1!
1(
1G
b0 E
1F
1%
#1380000
0!
0(
#1385000
1!
1(
b1 E
#1390000
0!
0(
#1395000
1!
1(
0G
b0 E
0F
0%
#1400000
0!
0(
#1405000
1!
1(
b1 E
#1410000
0!
0(
#1415000
1!
1(
b10 E
#1420000
0!
0(
#1425000
1!
1(
1G
b0 E
1F
1%
#1430000
0!
0(
b111 '
b111 $
11
1<
0C
1B
0D
#1435000
1!
1(
b1 E
#1440000
0!
0(
#1445000
1!
1(
b10 E
#1450000
0!
0(
#1455000
1!
1(
0G
b0 E
0F
0%
#1460000
0!
0(
#1465000
1!
1(
b1 E
#1470000
0!
0(
#1475000
1!
1(
b10 E
#1480000
0!
0(
#1485000
1!
1(
b11 E
#1490000
0!
0(
#1495000
1!
1(
1G
b0 E
1F
1%
#1500000
0!
0(
#1505000
1!
1(
b1 E
#1510000
0!
0(
#1515000
1!
1(
b10 E
#1520000
0!
0(
#1525000
1!
1(
0G
b0 E
0F
0%
#1530000
0!
0(
#1535000
1!
1(
b1 E
#1540000
0!
0(
#1545000
1!
1(
b10 E
#1550000
0!
0(
#1555000
1!
1(
b11 E
#1560000
0!
0(
#1565000
1!
1(
1G
b0 E
1F
1%
#1570000
0!
0(
#1575000
1!
1(
b1 E
#1580000
0!
0(
#1585000
1!
1(
b10 E
#1590000
0!
0(
#1595000
1!
1(
0G
b0 E
0F
0%
#1600000
0!
0(
#1605000
1!
1(
b1 E
#1610000
0!
0(
#1615000
1!
1(
b10 E
#1620000
0!
0(
#1625000
1!
1(
b11 E
#1630000
0!
0(
b1 '
b1 $
01
00
0<
0;
1C
1A
1@
1?
1>
1=
03
1D
0C
0B
0A
0@
0?
0>
0=
#1635000
1!
1(
1%
b0 E
